pycocoevalcap/eval.py
pycocoevalcap/bleu/bleu.py
pycocoevalcap/bleu/bleu_scorer.py
pycocoevalcap/cider/cider.py
pycocoevalcap/cider/cider_scorer.py
pycocoevalcap/example/coco_eval_example.py
pycocoevalcap/meteor/meteor-1.5.jar
pycocoevalcap/meteor/meteor.py
pycocoevalcap/meteor/data/paraphrase-en.gz
pycocoevalcap/rouge/rouge.py
pycocoevalcap/spice/__init__.py
pycocoevalcap/spice/get_stanford_models.py
pycocoevalcap/spice/spice-1.0.jar
pycocoevalcap/spice/spice.py
pycocoevalcap/spice/lib/Meteor-1.5.jar
pycocoevalcap/spice/lib/SceneGraphParser-1.0.jar
pycocoevalcap/spice/lib/ejml-0.23.jar
pycocoevalcap/spice/lib/fst-2.47.jar
pycocoevalcap/spice/lib/guava-19.0.jar
pycocoevalcap/spice/lib/hamcrest-core-1.3.jar
pycocoevalcap/spice/lib/jackson-core-2.5.3.jar
pycocoevalcap/spice/lib/javassist-3.19.0-GA.jar
pycocoevalcap/spice/lib/json-simple-1.1.1.jar
pycocoevalcap/spice/lib/junit-4.12.jar
pycocoevalcap/spice/lib/lmdbjni-0.4.6.jar
pycocoevalcap/spice/lib/lmdbjni-linux64-0.4.6.jar
pycocoevalcap/spice/lib/lmdbjni-osx64-0.4.6.jar
pycocoevalcap/spice/lib/lmdbjni-win64-0.4.6.jar
pycocoevalcap/spice/lib/objenesis-2.4.jar
pycocoevalcap/spice/lib/slf4j-api-1.7.12.jar
pycocoevalcap/spice/lib/slf4j-simple-1.7.21.jar
pycocoevalcap/tokenizer/ptbtokenizer.py
pycocoevalcap/tokenizer/stanford-corenlp-3.4.1.jar
pycocoevalcap-1.2.dist-info/METADATA
pycocoevalcap-1.2.dist-info/WHEEL
pycocoevalcap-1.2.dist-info/top_level.txt
pycocoevalcap-1.2.dist-info/RECORD
