Metadata-Version: 2.1
Name: pycocoevalcap
Version: 1.2
Summary: MS-COCO Caption Evaluation for Python 3
Home-page: https://github.com/salaniz/pycocoevalcap
Maintainer: salaniz
License: UNKNOWN
Platform: UNKNOWN
Requires-Python: >=3
